gstandaard/__init__.py
gstandaard/config.py
gstandaard/constants.py
gstandaard/db.py
gstandaard/definition.py
gstandaard/files.py
gstandaard/generate.py
gstandaard/model.py
gstandaard/parsing.py
gstandaard/populate.py
gstandaard/test.py
gstandaard/traversal.py
gstandaard/utils.py
gstandaard/wes.py
gstandaard-0.0.1.dist-info/LICENSE
gstandaard-0.0.1.dist-info/METADATA
gstandaard-0.0.1.dist-info/WHEEL
gstandaard-0.0.1.dist-info/top_level.txt
gstandaard-0.0.1.dist-info/RECORD
